{
  "events": [
    {
      "id": "1",
      "title": "Rails Conference 2025",
      "date": "2025-02-20",
      "description": "Join us for a day of insightful talks and networking with industry leaders in technology.",
      "location": "Convention Center, Downtown"
    },
    {
      "id": "2",
      "title": "Vue Conference 2025",
      "date": "2025-03-20",
      "description": "Join us for a day of insightful talks and networking with industry leaders in technology.",
      "location": "Convention Center, Downtown"
    },
    {
      "id": "3",
      "title": "PHP Conference 2025",
      "date": "2025-04-20",
      "description": "Join us for a day of insightful talks and networking with industry leaders in technology.",
      "location": "Convention Center, Downtown"
    },
    {
      "id": "4",
      "title": "Rust Conference 2025",
      "date": "2025-05-20",
      "description": "Join us for a day of insightful talks and networking with industry leaders in technology.",
      "location": "Convention Center, Downtown"
    }
  ],
  "bookings": [
    {
      "id": "1741710019743",
      "userId": 1,
      "eventId": "4",
      "eventTitle": "Rust Conference 2025",
      "status": "confirmed"
    }
  ]
}